{"total":28,"pageSize":12,"pageCount":3,"data":[{"title":"2021年度总结","uid":"10e799bf47669bd7fff35712248e1c6e","slug":"life/2021年度总结","date":"2021-12-31T12:25:41.000Z","updated":"2022-07-14T04:43:58.290Z","comments":true,"path":"api/articles/life/2021年度总结.json","cover":[],"text":" 前言写下此文的时候，2021已接近尾声，2022的钟声即将敲响，一年了，发生了什么呢，我又做成了什么呢… 月度 1月：创业园的师兄接到了个项目给我们做，起初这...","permalink":"/post/life/2021年度总结","photos":[],"count_time":{"symbolsCount":780,"symbolsTime":"1 mins."},"categories":[{"name":"生活","slug":"生活","count":4,"path":"api/categories/生活.json"}],"tags":[{"name":"人生","slug":"人生","count":2,"path":"api/tags/人生.json"},{"name":"2021","slug":"2021","count":1,"path":"api/tags/2021.json"},{"name":"总结","slug":"总结","count":1,"path":"api/tags/总结.json"}],"author":{"name":"Joshlee","slug":"blog-author","avatar":"/images/avatar.png","link":"/","description":"这个人很菜，什么也没有留下","socials":{}}},{"title":"How to Using FiddlerEverywhere","uid":"3f945107ce99195b9c8dafd2737a8d45","slug":"testing/Fiddler Everywhere抓包","date":"2021-12-30T02:43:04.000Z","updated":"2023-09-13T10:20:45.112Z","comments":true,"path":"api/articles/testing/Fiddler Everywhere抓包.json","cover":[],"text":" Fiddler EveryWhere 环境安装1. 安装Fiddler 功能强大，同时占用空间小，能记录所有的客户端和服务器端的 http 和https 请求...","permalink":"/post/testing/Fiddler Everywhere抓包","photos":[],"count_time":{"symbolsCount":"14k","symbolsTime":"13 mins."},"categories":[{"name":"测试","slug":"测试","count":1,"path":"api/categories/测试.json"}],"tags":[{"name":"软件测试","slug":"软件测试","count":1,"path":"api/tags/软件测试.json"}],"author":{"name":"Joshlee","slug":"blog-author","avatar":"/images/avatar.png","link":"/","description":"这个人很菜，什么也没有留下","socials":{}}},{"title":"《软件开发工具》","uid":"2cc8b90b0dba95b11728dd29144d57a6","slug":"examination/tool_for_software_development","date":"2021-10-03T11:37:25.000Z","updated":"2022-11-12T00:08:56.675Z","comments":true,"path":"api/articles/examination/tool_for_software_development.json","cover":[],"text":" 第1章 绪论软件产品的质量、效率、价格已成为各方关注的十分重要的问题。 1.1 软件开发工具的由来 操作系统、汇编程序、汇编系统时软件开发中必不可少的工具，但...","permalink":"/post/examination/tool_for_software_development","photos":[],"count_time":{"symbolsCount":"16k","symbolsTime":"15 mins."},"categories":[{"name":"应试","slug":"应试","count":5,"path":"api/categories/应试.json"}],"tags":[{"name":"升本","slug":"升本","count":3,"path":"api/tags/升本.json"},{"name":"自考","slug":"自考","count":2,"path":"api/tags/自考.json"}],"author":{"name":"Joshlee","slug":"blog-author","avatar":"/images/avatar.png","link":"/","description":"这个人很菜，什么也没有留下","socials":{}}},{"title":"《软件开发工具》","uid":"2cc8b90b0dba95b11728dd29144d57a6","slug":"examination/tool for software development","date":"2021-10-03T11:37:25.000Z","updated":"2022-11-12T00:08:57.662Z","comments":true,"path":"api/articles/examination/tool for software development.json","cover":[],"text":" 第1章 绪论软件产品的质量、效率、价格已成为各方关注的十分重要的问题。 1.1 软件开发工具的由来 操作系统、汇编程序、汇编系统时软件开发中必不可少的工具，但...","permalink":"/post/examination/tool for software development","photos":[],"count_time":{"symbolsCount":"16k","symbolsTime":"15 mins."},"categories":[{"name":"应试","slug":"应试","count":5,"path":"api/categories/应试.json"}],"tags":[{"name":"升本","slug":"升本","count":3,"path":"api/tags/升本.json"},{"name":"自考","slug":"自考","count":2,"path":"api/tags/自考.json"}],"author":{"name":"Joshlee","slug":"blog-author","avatar":"/images/avatar.png","link":"/","description":"这个人很菜，什么也没有留下","socials":{}}}]}