{"name":"应试","slug":"应试","count":6,"postlist":[{"title":"初识 CS 考研","uid":"a73e5b444f55a582b5586ab6d896a327","slug":"examination/cs_kaoyan","date":"2023-12-26T10:39:12.000Z","updated":"2023-12-27T02:53:15.328Z","comments":true,"path":"api/articles/examination/cs_kaoyan.json","keywords":null,"cover":null,"text":"考研时间节点 大纲更新阶段（8月底-9月中） 招生简章发布及考试大纲发布，考生可以了解到学校2022年的招新阶段和考试科目及大纲。 报名阶段（9月-12月） 考...","permalink":"/post/examination/cs_kaoyan","photos":[],"count_time":{"symbolsCount":"1.3k","symbolsTime":"1 mins."},"categories":[{"name":"应试","slug":"应试","count":6,"path":"api/categories/应试.json"}],"tags":[{"name":"考研","slug":"考研","count":3,"path":"api/tags/考研.json"}],"author":{"name":"Joshlee","slug":"blog-author","avatar":"/images/avatar.png","link":"/","description":"这个人很菜，什么也没有留下","socials":{}},"feature":true},{"title":"我的专升本心路历程","uid":"3217b66f0cb1b9a96a16a01e025f7ee8","slug":"examination/zhuanshengben_review","date":"2023-05-25T11:54:02.000Z","updated":"2023-12-24T02:14:47.695Z","comments":true,"path":"api/articles/examination/zhuanshengben_review.json","keywords":null,"cover":[],"text":"2023年广东普通专升本碎碎念对于这次考试，我的自我评价是：寄！ 在我大一大二的时候，总能听到师兄师姐们说：插本？很简单的啦，比高考还简单，一月份（大概三、四月...","permalink":"/post/examination/zhuanshengben_review","photos":[],"count_time":{"symbolsCount":"4.3k","symbolsTime":"4 mins."},"categories":[{"name":"应试","slug":"应试","count":6,"path":"api/categories/应试.json"}],"tags":[{"name":"复盘","slug":"复盘","count":1,"path":"api/tags/复盘.json"}],"author":{"name":"Joshlee","slug":"blog-author","avatar":"/images/avatar.png","link":"/","description":"这个人很菜，什么也没有留下","socials":{}}},{"title":"广东普通专升本考纲(计算机)","uid":"e844d1ea81af098142e44cbca9914529","slug":"examination/zhuanshengben_outline","date":"2023-01-06T08:36:43.000Z","updated":"2023-08-21T14:06:05.000Z","comments":true,"path":"api/articles/examination/zhuanshengben_outline.json","keywords":null,"cover":null,"text":" 2023 加深字体为变动部分 一、政治理论考试范围马克思主义中国化的历史进程与理论成果；毛泽东思想及其历史地位；新民主主义革命理论；社会主义改造理论；社会主义...","permalink":"/post/examination/zhuanshengben_outline","photos":[],"count_time":{"symbolsCount":"3.8k","symbolsTime":"3 mins."},"categories":[{"name":"应试","slug":"应试","count":6,"path":"api/categories/应试.json"}],"tags":[{"name":"升本","slug":"升本","count":3,"path":"api/tags/升本.json"},{"name":"考纲","slug":"考纲","count":1,"path":"api/tags/考纲.json"}],"author":{"name":"Joshlee","slug":"blog-author","avatar":"/images/avatar.png","link":"/","description":"这个人很菜，什么也没有留下","socials":{}}},{"title":"阿里云 ACP 云原生微服务","uid":"31cb8022faa8493f1aedc9b9cc8dea4f","slug":"examination/AliyunACP","date":"2022-07-27T00:59:03.000Z","updated":"2023-08-18T06:20:35.000Z","comments":true,"path":"api/articles/examination/AliyunACP.json","keywords":null,"cover":[],"text":" 考点总结 ","permalink":"/post/examination/AliyunACP","photos":[],"count_time":{"symbolsCount":7,"symbolsTime":"1 mins."},"categories":[{"name":"应试","slug":"应试","count":6,"path":"api/categories/应试.json"}],"tags":[{"name":"考证","slug":"考证","count":1,"path":"api/tags/考证.json"}],"author":{"name":"Joshlee","slug":"blog-author","avatar":"/images/avatar.png","link":"/","description":"这个人很菜，什么也没有留下","socials":{}}},{"title":"《软件开发工具》","uid":"2cc8b90b0dba95b11728dd29144d57a6","slug":"examination/tool_for_software_development","date":"2021-10-03T11:37:25.000Z","updated":"2022-11-12T00:08:56.000Z","comments":true,"path":"api/articles/examination/tool_for_software_development.json","keywords":null,"cover":[],"text":" 第1章 绪论软件产品的质量、效率、价格已成为各方关注的十分重要的问题。 1.1 软件开发工具的由来 操作系统、汇编程序、汇编系统时软件开发中必不可少的工具，但...","permalink":"/post/examination/tool_for_software_development","photos":[],"count_time":{"symbolsCount":"16k","symbolsTime":"15 mins."},"categories":[{"name":"应试","slug":"应试","count":6,"path":"api/categories/应试.json"}],"tags":[{"name":"自考","slug":"自考","count":2,"path":"api/tags/自考.json"},{"name":"升本","slug":"升本","count":3,"path":"api/tags/升本.json"}],"author":{"name":"Joshlee","slug":"blog-author","avatar":"/images/avatar.png","link":"/","description":"这个人很菜，什么也没有留下","socials":{}}},{"title":"《软件开发工具》","uid":"2cc8b90b0dba95b11728dd29144d57a6","slug":"examination/tool for software development","date":"2021-10-03T11:37:25.000Z","updated":"2022-11-12T00:08:57.000Z","comments":true,"path":"api/articles/examination/tool for software development.json","keywords":null,"cover":[],"text":" 第1章 绪论软件产品的质量、效率、价格已成为各方关注的十分重要的问题。 1.1 软件开发工具的由来 操作系统、汇编程序、汇编系统时软件开发中必不可少的工具，但...","permalink":"/post/examination/tool for software development","photos":[],"count_time":{"symbolsCount":"16k","symbolsTime":"15 mins."},"categories":[{"name":"应试","slug":"应试","count":6,"path":"api/categories/应试.json"}],"tags":[{"name":"自考","slug":"自考","count":2,"path":"api/tags/自考.json"},{"name":"升本","slug":"升本","count":3,"path":"api/tags/升本.json"}],"author":{"name":"Joshlee","slug":"blog-author","avatar":"/images/avatar.png","link":"/","description":"这个人很菜，什么也没有留下","socials":{}}}]}