{"title":"阿里云 ACP 云原生微服务","uid":"31cb8022faa8493f1aedc9b9cc8dea4f","slug":"exam/AliyunACP","date":"2022-07-27T00:59:03.000Z","updated":"2022-08-21T17:02:53.515Z","comments":true,"path":"api/articles/exam/AliyunACP.json","keywords":null,"cover":[],"content":"<meta name=\"referrer\" content=\"no-referrer\"/>\n\n<h2 id=\"考点总结\"><a href=\"#考点总结\" class=\"headerlink\" title=\"考点总结\"></a>考点总结</h2><p><img src=\"/images/ACP.png\" alt=\"img\"></p>\n","text":" 考点总结 ","link":"","photos":[],"count_time":{"symbolsCount":7,"symbolsTime":"1 mins."},"categories":[{"name":"应试","slug":"应试","count":4,"path":"api/categories/应试.json"}],"tags":[{"name":"考证","slug":"考证","count":1,"path":"api/tags/考证.json"}],"toc":"<ol class=\"toc\"><li class=\"toc-item toc-level-2\"><a class=\"toc-link\" href=\"#%E8%80%83%E7%82%B9%E6%80%BB%E7%BB%93\"><span class=\"toc-text\">考点总结</span></a></li></ol>","author":{"name":"Jx","slug":"blog-author","avatar":"/images/avatar.png","link":"/","description":"这个人很菜，什么也没有留下","socials":{"github":"","twitter":"","stackoverflow":"","wechat":"","qq":"","weibo":"","zhihu":"","csdn":"","juejin":"","customs":{}}},"mapped":true,"prev_post":{"title":"Using Clash in Linux Server","uid":"44e789181d3b4bef6dfcd4ebb07b6454","slug":"system/Using Clash in Linux Server","date":"2022-08-07T01:34:49.000Z","updated":"2022-08-07T02:12:57.693Z","comments":true,"path":"api/articles/system/Using Clash in Linux Server.json","keywords":null,"cover":null,"text":" Background: Too slow to install some dependent environments DownloadWe can go to the Clash Releases Page and find the corresponding system ...","link":"","photos":[],"count_time":{"symbolsCount":"1.1k","symbolsTime":"1 mins."},"categories":[{"name":"操作系统","slug":"操作系统","count":2,"path":"api/categories/操作系统.json"}],"tags":[{"name":"linux","slug":"linux","count":2,"path":"api/tags/linux.json"}],"author":{"name":"Jx","slug":"blog-author","avatar":"/images/avatar.png","link":"/","description":"这个人很菜，什么也没有留下","socials":{"github":"","twitter":"","stackoverflow":"","wechat":"","qq":"","weibo":"","zhihu":"","csdn":"","juejin":"","customs":{}}}},"next_post":{"title":"一些好用但鲜为人知的 Linux 命令","uid":"5e7254d63639ed21d8e1e8e2812eb98c","slug":"system/Some important Linux commands","date":"2022-07-08T03:15:20.000Z","updated":"2022-07-14T04:43:58.290Z","comments":true,"path":"api/articles/system/Some important Linux commands.json","keywords":null,"cover":null,"text":"系统监视UptimeUptime会返回服务器运行时长、当前时间、用户数量和内存使用平均数等信息。 $ uptime WallWall可以向当前登录到系统的每个人的终端发送消息 $ wall &quot;Your message&quot; Top实时显示 CPU 和内存使用情况的...","link":"","photos":[],"count_time":{"symbolsCount":"2.2k","symbolsTime":"2 mins."},"categories":[{"name":"操作系统","slug":"操作系统","count":2,"path":"api/categories/操作系统.json"}],"tags":[{"name":"linux","slug":"linux","count":2,"path":"api/tags/linux.json"}],"author":{"name":"Jx","slug":"blog-author","avatar":"/images/avatar.png","link":"/","description":"这个人很菜，什么也没有留下","socials":{"github":"","twitter":"","stackoverflow":"","wechat":"","qq":"","weibo":"","zhihu":"","csdn":"","juejin":"","customs":{}}}}}